robin/__init__.py
robin.io_py-0.0.8.dist-info/METADATA
robin.io_py-0.0.8.dist-info/WHEEL
robin.io_py-0.0.8.dist-info/top_level.txt
robin.io_py-0.0.8.dist-info/RECORD
