Metadata-Version: 2.1
Name: robin.io-py
Version: 0.0.8
Summary: Robin.io-py is a Python SDK built to communicate with the Robinapp API. Now you can integrate Robin.io with minimal effort and quickly setup a real-time messaging platform in your Web application.
Home-page: https://github.com/robin-io/robin.io-py/
Author: Samuel Olufeko
Author-email: samuel@acumen.digital
License: MIT
Keywords: notifications python library
Platform: UNKNOWN
Classifier: Intended Audience :: Developers
Classifier: License :: OSI Approved :: MIT License
Classifier: Programming Language :: Python :: 3
Classifier: Programming Language :: Python :: 3.9
Requires-Dist: requests
Requires-Dist: websocket-client
